{
  "CALL_US_FOR_HELP": "Si vous avez des questions ou si vous n'avez pas demandé la réinitialisation de votre mot de passe, appelez-nous au 1-800-223-7440, entre 7 h et 2 h (HE).", 
  "EXPIRED_PASSWORD": "Le mot de passe de votre compte labaie.com est expiré. Veuillez réinitialiser votre mot de passe ci-dessous.", 
  "RESET_PASSWORD_EMAIL_SITE_REFER": "bmLocale=fr_CA&site_refer=", 
  "RESET_PASSWORD_ACCOUNT_LINK": "{account_base_page}\/reinitialiser-le-mot-de-passe", 
  "RESET_PASSWORD_EMAIL_SUBJECT": "Réinitialisation du mot de passe de votre compte labaie.com",
  "RESET_PASSWORD_EMAIL_CONTENT": "<p>Bonjour {first_name} {last_name}, <\/p>\\ <p>Vous avez récemment demandé la réinitialisation du mot de passe de votre compte labaie.com. Veuillez cliquer sur le lien ci-dessous pour réinitialiser votre mot de passe : <\/p>\\ {reset_link} <\/p>\\ <p>Pour des raisons de sécurité, ce lien expirera après 24 heures. <\/p>\\ <p>Si vous avez des questions ou si vous n'avez pas demandé la réinitialisation de votre mot de passe, appelez-nous au 1-800-223-7440, entre 7 h et 2 h (HE). <\/p>\\ <p>Sincères salutations. <\/p>\\ <p>Service à la clientèle de La Baie d'Hudson <\/p>\\ <p>labaie.com<\/p>"
}